PyFPT-1.0.2.dist-info/WHEEL
PyFPT-1.0.2.dist-info/LICENSE
PyFPT-1.0.2.dist-info/top_level.txt
PyFPT-1.0.2.dist-info/RECORD
PyFPT-1.0.2.dist-info/METADATA
pyfpt/__init__.py
pyfpt/analytics/reduced_potential_diff.py
pyfpt/analytics/reduced_potential.py
pyfpt/analytics/classicality_criterion.py
pyfpt/analytics/optimal_bias_amplitude.py
pyfpt/analytics/quadratic_inflation_large_mass_pdf.py
pyfpt/analytics/mean_efolds.py
pyfpt/analytics/slow_roll_drift.py
pyfpt/analytics/skewness_efolds.py
pyfpt/analytics/third_central_moment_efolds.py
pyfpt/analytics/slow_roll_diffusion.py
pyfpt/analytics/gaussian_deviation.py
pyfpt/analytics/quadratic_inflation_near_tail_pdf.py
pyfpt/analytics/gaussian_pdf.py
pyfpt/analytics/reduced_potential_ddiff.py
pyfpt/analytics/edgeworth_pdf.py
pyfpt/analytics/fourth_central_moment_efolds.py
pyfpt/analytics/__init__.py
pyfpt/analytics/kurtosis_efolds.py
pyfpt/analytics/variance_efolds.py
pyfpt/numerics/data_points_pdf.py
pyfpt/numerics/save_data_to_file.py
pyfpt/numerics/log_normal_error.py
pyfpt/numerics/log_normal_height.py
pyfpt/numerics/lognormality_check.py
pyfpt/numerics/histogram_data_truncation.py
pyfpt/numerics/histogram_normalisation.py
pyfpt/numerics/jackknife_errors.py
pyfpt/numerics/multi_processing_error.py
pyfpt/numerics/re_processing.py
pyfpt/numerics/is_simulation.py
pyfpt/numerics/importance_sampling_cython.cpython-38-x86_64-linux-gnu.so
pyfpt/numerics/log_normal_mean.py
pyfpt/numerics/__init__.py
pyfpt/numerics/data_in_histogram_bins.py
