Metadata-Version: 2.1
Name: PyFPT
Version: 1.0.2
Summary: Stochastic first-passage time (FPT) simulations using importance sampling
Home-page: https://github.com/Jacks0nJ/PyFPT.git
Author: Joe Jackson
Author-email: joseph.jackson@port.ac.uk
Project-URL: Bug Tracker, https://github.com/Jacks0nJ/PyFPT/issues
Classifier: Programming Language :: Python :: 3
Classifier: License :: OSI Approved :: Apache Software License
Requires-Python: >=3.6
License-File: LICENSE
Requires-Dist: matplotlib
Requires-Dist: mpmath
Requires-Dist: numpy
Requires-Dist: scipy
Requires-Dist: pandas
